mkdocs_webcontext_plugin/__init__.py
mkdocs_webcontext_plugin/plugin.py
mkdocs_webcontext_plugin-0.1.1.dist-info/licenses/LICENSE
mkdocs_webcontext_plugin-0.1.1.dist-info/METADATA
mkdocs_webcontext_plugin-0.1.1.dist-info/WHEEL
mkdocs_webcontext_plugin-0.1.1.dist-info/entry_points.txt
mkdocs_webcontext_plugin-0.1.1.dist-info/top_level.txt
mkdocs_webcontext_plugin-0.1.1.dist-info/RECORD
