Metadata-Version: 2.4
Name: mkdocs-webcontext-plugin
Version: 0.1.1
Summary: Mkdocs plugin to convert absolute paths to Webcontext aware paths.
Home-page: https://github.com/darrelk/mkdocs-webcontext-plugin
Author: darrelk
Author-email: darrelkley@gmail.com
License: MIT
License-File: LICENSE
Dynamic: author
Dynamic: author-email
Dynamic: description
Dynamic: description-content-type
Dynamic: home-page
Dynamic: license
Dynamic: license-file
Dynamic: summary
